commandsession/__init__.py
commandsession/commandsession.py
commandsession-0.1.dist-info/DESCRIPTION.rst
commandsession-0.1.dist-info/METADATA
commandsession-0.1.dist-info/metadata.json
commandsession-0.1.dist-info/RECORD
commandsession-0.1.dist-info/top_level.txt
commandsession-0.1.dist-info/WHEEL
