Metadata-Version: 2.0
Name: commandsession
Version: 0.1
Summary: Small session wrapper for subprocess popen helpers.
Home-page: https://github.com/mikewaters/command-session
Author: Mike Waters
Author-email: robert.waters@gmail.com
License: MIT
Keywords: commandsession
Platform: UNKNOWN
Classifier: Development Status :: 2 - Pre-Alpha
Classifier: Intended Audience :: Developers
Classifier: License :: OSI Approved :: MIT License
Classifier: Natural Language :: English
Requires-Dist: boltons
